MANIFEST.in
README.rst
setup.py
kkk/Reverse_Int.py
kkk/__init__.py
rrr.egg-info/PKG-INFO
rrr.egg-info/SOURCES.txt
rrr.egg-info/dependency_links.txt
rrr.egg-info/requires.txt
rrr.egg-info/top_level.txt